MANIFEST.in
README.md
cre2.cpp
setup.py
cffi_re2/__init__.py
cffi_re2.egg-info/PKG-INFO
cffi_re2.egg-info/SOURCES.txt
cffi_re2.egg-info/dependency_links.txt
cffi_re2.egg-info/not-zip-safe
cffi_re2.egg-info/requires.txt
cffi_re2.egg-info/top_level.txt