Metadata-Version: 1.0
Name: cffi-re2
Version: 0.2.1
Summary: Access re2 library using cffi
Home-page: https://github.com/vls/cffi_re2
Author: UNKNOWN
Author-email: UNKNOWN
License: MIT license
Platform: UNKNOWN
